myrrh/core/interfaces/__init__.py
myrrh/core/interfaces/ientity.py
myrrh/core/interfaces/ieservices.py
myrrh/core/interfaces/iesystem.py
myrrh/core/interfaces/iprovider.py
myrrh/core/interfaces/iservices.py
myrrh_core_api-0.1.0.dist-info/AUTHORS.md
myrrh_core_api-0.1.0.dist-info/LICENSE
myrrh_core_api-0.1.0.dist-info/METADATA
myrrh_core_api-0.1.0.dist-info/WHEEL
myrrh_core_api-0.1.0.dist-info/top_level.txt
myrrh_core_api-0.1.0.dist-info/RECORD
